irk/__init__.py
irk/main.py
irk/commands/__init__.py
irk/commands/install.py
irk/commands/remove.py
irk/commands/update.py
irk/installers/__init__.py
irk/installers/aptinstall.py
irk/installers/common.py
irk/installers/pipinstall.py
irk/installers/script.py
irk/resolvers/__init__.py
irk/resolvers/aptresolver.py
irk/resolvers/common.py
irk/resolvers/customresolver.py
irk/resolvers/pipresolver.py
irk/util/__init__.py
irk/util/proc.py
irk/util/version.py
irk/util/storage/__init__.py
irk/util/storage/database.py
irk/util/storage/etcfile.py
irk/util/storage/resolv.py
irk-0.2.dist-info/DESCRIPTION.rst
irk-0.2.dist-info/METADATA
irk-0.2.dist-info/RECORD
irk-0.2.dist-info/WHEEL
irk-0.2.dist-info/entry_points.txt
irk-0.2.dist-info/metadata.json
irk-0.2.dist-info/top_level.txt
