Metadata-Version: 2.0
Name: irk
Version: 0.2
Summary: A meta package manager
Home-page: https://github.com/mincrmatt12/irk
Author: mincrmatt12
Author-email: UNKNOWN
License: GPLv3
Platform: UNKNOWN
Requires-Dist: click
Requires-Dist: requests
Requires-Dist: requests-file
